[{"descriptionId":600022,"color":11582132,"assetId":1,"nameId":493275,"id":1},{"descriptionId":600028,"color":2990223,"assetId":2,"nameId":491739,"id":2},{"descriptionId":600026,"color":15700480,"assetId":3,"nameId":491757,"id":3},{"descriptionId":600027,"color":12845166,"assetId":4,"nameId":491775,"id":4},{"descriptionId":600021,"color":13380864,"assetId":5,"nameId":491793,"id":5},{"descriptionId":600025,"color":9220354,"assetId":6,"nameId":491811,"id":6},{"descriptionId":600024,"color":6501794,"assetId":7,"nameId":492211,"id":7},{"descriptionId":600019,"color":551590,"assetId":8,"nameId":491847,"id":8}]