[{"statPerLevelRange":[[1.0,3.0],[50.0,3.0],[100.0,5.0],[150.0,7.0],[200.0,9.0]],"caracId":25,"companionId":1,"id":5,"order":5},{"statPerLevelRange":[[1.0,55.0],[50.0,5.0],[100.0,10.0],[150.0,20.0],[200.0,40.0]],"caracId":0,"companionId":1,"id":8,"order":0},{"statPerLevelRange":[[200.0,0.375]],"caracId":78,"companionId":1,"id":9,"order":8},{"statPerLevelRange":[[200.0,0.4]],"caracId":27,"companionId":1,"id":10,"order":6},{"statPerLevelRange":[[1.0,12.0]],"caracId":36,"companionId":1,"id":11,"order":13},{"statPerLevelRange":[[1.0,12.0]],"caracId":37,"companionId":1,"id":12,"order":14},{"statPerLevelRange":[[1.0,12.0]],"caracId":35,"companionId":1,"id":13,"order":12},{"statPerLevelRange":[[1.0,12.0]],"caracId":34,"companionId":1,"id":14,"order":11},{"statPerLevelRange":[[1.0,12.0]],"caracId":33,"companionId":1,"id":15,"order":10},{"statPerLevelRange":[[1.0,6.0],[200.0,0.029]],"caracId":1,"companionId":1,"id":16,"order":1},{"statPerLevelRange":[[1.0,3.0],[200.0,0.017]],"caracId":23,"companionId":1,"id":17,"order":2},{"statPerLevelRange":[[200.0,0.02]],"caracId":19,"companionId":1,"id":18,"order":3},{"statPerLevelRange":[[200.0,0.15]],"caracId":79,"companionId":1,"id":19,"order":9},{"statPerLevelRange":[[200.0,0.3]],"caracId":28,"companionId":1,"id":20,"order":7},{"statPerLevelRange":[[1.0,0.2],[50.0,0.2],[100.0,0.4],[150.0,0.6],[200.0,0.8]],"caracId":16,"companionId":1,"id":21,"order":4},{"statPerLevelRange":[[1.0,3.0],[50.0,3.0],[100.0,5.0],[150.0,7.0],[200.0,9.0]],"caracId":25,"companionId":2,"id":22,"order":5},{"statPerLevelRange":[[1.0,55.0],[50.0,5.0],[100.0,10.0],[150.0,20.0],[200.0,40.0]],"caracId":0,"companionId":2,"id":23,"order":0},{"statPerLevelRange":[[200.0,0.375]],"caracId":78,"companionId":2,"id":24,"order":8},{"statPerLevelRange":[[200.0,0.3]],"caracId":27,"companionId":2,"id":25,"order":6},{"statPerLevelRange":[[1.0,10.0]],"caracId":36,"companionId":2,"id":26,"order":13},{"statPerLevelRange":[[1.0,10.0]],"caracId":37,"companionId":2,"id":27,"order":14},{"statPerLevelRange":[[1.0,10.0]],"caracId":35,"companionId":2,"id":28,"order":12},{"statPerLevelRange":[[1.0,20.0]],"caracId":34,"companionId":2,"id":29,"order":11},{"statPerLevelRange":[[1.0,10.0]],"caracId":33,"companionId":2,"id":30,"order":10},{"statPerLevelRange":[[1.0,6.0],[200.0,0.033]],"caracId":1,"companionId":2,"id":31,"order":1},{"statPerLevelRange":[[1.0,3.0],[200.0,0.014]],"caracId":23,"companionId":2,"id":32,"order":2},{"statPerLevelRange":[[200.0,0.02]],"caracId":19,"companionId":2,"id":33,"order":3},{"statPerLevelRange":[[200.0,0.15]],"caracId":79,"companionId":2,"id":34,"order":9},{"statPerLevelRange":[[200.0,0.4]],"caracId":28,"companionId":2,"id":35,"order":7},{"statPerLevelRange":[[1.0,0.2],[50.0,0.2],[100.0,0.4],[150.0,0.6],[200.0,0.8]],"caracId":16,"companionId":2,"id":36,"order":4},{"statPerLevelRange":[[1.0,3.0],[50.0,3.0],[100.0,5.0],[150.0,7.0],[200.0,9.0]],"caracId":25,"companionId":7,"id":51,"order":5},{"statPerLevelRange":[[1.0,55.0],[50.0,5.0],[100.0,10.0],[150.0,20.0],[200.0,40.0]],"caracId":0,"companionId":7,"id":52,"order":0},{"statPerLevelRange":[[200.0,0.3]],"caracId":78,"companionId":7,"id":53,"order":8},{"statPerLevelRange":[[200.0,0.3]],"caracId":27,"companionId":7,"id":54,"order":6},{"statPerLevelRange":[[1.0,10.0]],"caracId":36,"companionId":7,"id":55,"order":14},{"statPerLevelRange":[[1.0,10.0]],"caracId":37,"companionId":7,"id":56,"order":15},{"statPerLevelRange":[[1.0,10.0]],"caracId":35,"companionId":7,"id":57,"order":13},{"statPerLevelRange":[[1.0,10.0]],"caracId":34,"companionId":7,"id":58,"order":12},{"statPerLevelRange":[[1.0,20.0]],"caracId":33,"companionId":7,"id":59,"order":11},{"statPerLevelRange":[[1.0,6.0],[200.0,0.029]],"caracId":1,"companionId":7,"id":60,"order":1},{"statPerLevelRange":[[1.0,3.0],[200.0,0.017]],"caracId":23,"companionId":7,"id":61,"order":2},{"statPerLevelRange":[[200.0,0.15]],"caracId":79,"companionId":7,"id":62,"order":9},{"statPerLevelRange":[[200.0,0.3]],"caracId":28,"companionId":7,"id":63,"order":7},{"statPerLevelRange":[[1.0,0.2],[50.0,0.2],[100.0,0.4],[150.0,0.6],[200.0,0.8]],"caracId":16,"companionId":7,"id":64,"order":4},{"statPerLevelRange":[[200.0,0.033]],"caracId":19,"companionId":7,"id":65,"order":3},{"statPerLevelRange":[[200.0,0.4]],"caracId":83,"companionId":7,"id":66,"order":10},{"statPerLevelRange":[[1.0,3.0],[50.0,3.0],[100.0,5.0],[150.0,7.0],[200.0,9.0]],"caracId":25,"companionId":8,"id":67,"order":5},{"statPerLevelRange":[[1.0,55.0],[50.0,5.0],[100.0,10.0],[150.0,20.0],[200.0,40.0]],"caracId":0,"companionId":8,"id":68,"order":0},{"statPerLevelRange":[[200.0,0.15]],"caracId":78,"companionId":8,"id":69,"order":8},{"statPerLevelRange":[[200.0,0.3]],"caracId":27,"companionId":8,"id":70,"order":6},{"statPerLevelRange":[[1.0,10.0]],"caracId":36,"companionId":8,"id":71,"order":15},{"statPerLevelRange":[[1.0,10.0]],"caracId":37,"companionId":8,"id":72,"order":16},{"statPerLevelRange":[[1.0,20.0]],"caracId":35,"companionId":8,"id":73,"order":14},{"statPerLevelRange":[[1.0,10.0]],"caracId":34,"companionId":8,"id":74,"order":13},{"statPerLevelRange":[[1.0,10.0]],"caracId":33,"companionId":8,"id":75,"order":12},{"statPerLevelRange":[[1.0,6.0],[200.0,0.022]],"caracId":1,"companionId":8,"id":76,"order":1},{"statPerLevelRange":[[1.0,3.0],[200.0,0.022]],"caracId":23,"companionId":8,"id":77,"order":2},{"statPerLevelRange":[[200.0,0.375]],"caracId":79,"companionId":8,"id":78,"order":9},{"statPerLevelRange":[[200.0,0.3]],"caracId":28,"companionId":8,"id":79,"order":7},{"statPerLevelRange":[[1.0,0.2],[50.0,0.2],[100.0,0.4],[150.0,0.6],[200.0,0.8]],"caracId":16,"companionId":8,"id":80,"order":4},{"statPerLevelRange":[[200.0,0.025]],"caracId":19,"companionId":8,"id":81,"order":3},{"statPerLevelRange":[[200.0,0.4]],"caracId":83,"companionId":8,"id":82,"order":10},{"statPerLevelRange":[[1.0,3.0],[50.0,3.0],[100.0,5.0],[150.0,7.0],[200.0,9.0]],"caracId":25,"companionId":9,"id":83,"order":4},{"statPerLevelRange":[[1.0,55.0],[50.0,5.0],[100.0,10.0],[150.0,20.0],[200.0,40.0]],"caracId":0,"companionId":9,"id":84,"order":0},{"statPerLevelRange":[[200.0,0.3]],"caracId":78,"companionId":9,"id":85,"order":7},{"statPerLevelRange":[[200.0,0.4]],"caracId":27,"companionId":9,"id":86,"order":5},{"statPerLevelRange":[[1.0,12.0]],"caracId":36,"companionId":9,"id":87,"order":13},{"statPerLevelRange":[[1.0,12.0]],"caracId":37,"companionId":9,"id":88,"order":14},{"statPerLevelRange":[[1.0,12.0]],"caracId":35,"companionId":9,"id":89,"order":12},{"statPerLevelRange":[[1.0,12.0]],"caracId":34,"companionId":9,"id":90,"order":11},{"statPerLevelRange":[[1.0,12.0]],"caracId":33,"companionId":9,"id":91,"order":10},{"statPerLevelRange":[[1.0,6.0],[200.0,0.029]],"caracId":1,"companionId":9,"id":92,"order":1},{"statPerLevelRange":[[1.0,3.0],[200.0,0.017]],"caracId":23,"companionId":9,"id":93,"order":2},{"statPerLevelRange":[[200.0,0.3]],"caracId":79,"companionId":9,"id":94,"order":8},{"statPerLevelRange":[[200.0,0.4]],"caracId":28,"companionId":9,"id":95,"order":6},{"statPerLevelRange":[[1.0,0.2],[50.0,0.2],[100.0,0.4],[150.0,0.6],[200.0,0.8]],"caracId":16,"companionId":9,"id":96,"order":3},{"statPerLevelRange":[[1.0,3.0],[50.0,3.0],[100.0,5.0],[150.0,7.0],[200.0,9.0]],"caracId":25,"companionId":6,"id":97,"order":4},{"statPerLevelRange":[[1.0,56.0],[50.0,6.0],[100.0,12.0],[150.0,24.0],[200.0,48.0]],"caracId":0,"companionId":6,"id":98,"order":0},{"statPerLevelRange":[[1.0,20.0]],"caracId":36,"companionId":6,"id":99,"order":13},{"statPerLevelRange":[[1.0,10.0]],"caracId":37,"companionId":6,"id":100,"order":14},{"statPerLevelRange":[[1.0,10.0]],"caracId":35,"companionId":6,"id":101,"order":12},{"statPerLevelRange":[[1.0,10.0]],"caracId":34,"companionId":6,"id":102,"order":11},{"statPerLevelRange":[[1.0,10.0]],"caracId":33,"companionId":6,"id":103,"order":10},{"statPerLevelRange":[[1.0,6.0],[200.0,0.029]],"caracId":1,"companionId":6,"id":104,"order":1},{"statPerLevelRange":[[1.0,3.0],[200.0,0.017]],"caracId":23,"companionId":6,"id":105,"order":2},{"statPerLevelRange":[[200.0,0.15]],"caracId":78,"companionId":6,"id":106,"order":7},{"statPerLevelRange":[[200.0,0.3]],"caracId":27,"companionId":6,"id":107,"order":5},{"statPerLevelRange":[[200.0,0.375]],"caracId":79,"companionId":6,"id":108,"order":8},{"statPerLevelRange":[[200.0,0.4]],"caracId":28,"companionId":6,"id":109,"order":6},{"statPerLevelRange":[[1.0,0.2],[50.0,0.2],[100.0,0.4],[150.0,0.6],[200.0,0.8]],"caracId":16,"companionId":6,"id":110,"order":3},{"statPerLevelRange":[[1.0,55.0],[50.0,5.0],[100.0,10.0],[150.0,20.0],[200.0,40.0]],"caracId":0,"companionId":11,"id":126,"order":0},{"statPerLevelRange":[[200.0,0.3]],"caracId":27,"companionId":11,"id":127,"order":6},{"statPerLevelRange":[[1.0,12.0]],"caracId":36,"companionId":11,"id":128,"order":13},{"statPerLevelRange":[[1.0,12.0]],"caracId":37,"companionId":11,"id":129,"order":14},{"statPerLevelRange":[[1.0,12.0]],"caracId":35,"companionId":11,"id":130,"order":12},{"statPerLevelRange":[[1.0,12.0]],"caracId":34,"companionId":11,"id":131,"order":11},{"statPerLevelRange":[[1.0,12.0]],"caracId":33,"companionId":11,"id":132,"order":10},{"statPerLevelRange":[[1.0,6.0],[200.0,0.029]],"caracId":1,"companionId":11,"id":133,"order":1},{"statPerLevelRange":[[1.0,3.0],[200.0,0.017]],"caracId":23,"companionId":11,"id":134,"order":2},{"statPerLevelRange":[[200.0,0.3]],"caracId":28,"companionId":11,"id":135,"order":7},{"statPerLevelRange":[[200.0,0.017]],"caracId":19,"companionId":11,"id":136,"order":3},{"statPerLevelRange":[[1.0,0.2],[50.0,0.2],[100.0,0.4],[150.0,0.6],[200.0,0.8]],"caracId":16,"companionId":11,"id":137,"order":4},{"statPerLevelRange":[[1.0,3.0],[50.0,3.0],[100.0,5.0],[150.0,7.0],[200.0,9.0]],"caracId":25,"companionId":11,"id":138,"order":5},{"statPerLevelRange":[[200.0,0.3]],"caracId":78,"companionId":11,"id":139,"order":8},{"statPerLevelRange":[[200.0,0.3]],"caracId":79,"companionId":11,"id":140,"order":9},{"statPerLevelRange":[[200.0,0.4]],"caracId":84,"companionId":8,"id":141,"order":11},{"statPerLevelRange":[[200.0,0.4]],"caracId":85,"companionId":6,"id":142,"order":9},{"statPerLevelRange":[[200.0,0.4]],"caracId":83,"companionId":9,"id":143,"order":9},{"statPerLevelRange":[[1.0,100.0]],"caracId":48,"companionId":11,"id":144,"order":15},{"statPerLevelRange":[[1.0,100.0]],"caracId":48,"companionId":8,"id":145,"order":17},{"statPerLevelRange":[[1.0,100.0]],"caracId":48,"companionId":1,"id":146,"order":15},{"statPerLevelRange":[[1.0,100.0]],"caracId":48,"companionId":6,"id":147,"order":15},{"statPerLevelRange":[[1.0,100.0]],"caracId":48,"companionId":9,"id":148,"order":15},{"statPerLevelRange":[[1.0,100.0]],"caracId":48,"companionId":7,"id":149,"order":16},{"statPerLevelRange":[[1.0,100.0]],"caracId":48,"companionId":2,"id":150,"order":15},{"statPerLevelRange":[[1.0,54.0],[50.0,4.0],[100.0,8.0],[150.0,16.0],[200.0,32.0]],"caracId":0,"companionId":12,"id":151,"order":0},{"statPerLevelRange":[[1.0,6.0],[200.0,0.029]],"caracId":1,"companionId":12,"id":152,"order":1},{"statPerLevelRange":[[1.0,3.0],[200.0,0.017]],"caracId":23,"companionId":12,"id":153,"order":2},{"statPerLevelRange":[[1.0,0.2],[50.0,0.2],[100.0,0.4],[150.0,0.6],[200.0,0.8]],"caracId":16,"companionId":12,"id":154,"order":3},{"statPerLevelRange":[[1.0,3.0],[50.0,3.0],[100.0,5.0],[150.0,7.0],[200.0,9.0]],"caracId":25,"companionId":12,"id":155,"order":4},{"statPerLevelRange":[[200.0,0.3]],"caracId":27,"companionId":12,"id":156,"order":5},{"statPerLevelRange":[[200.0,0.3]],"caracId":28,"companionId":12,"id":157,"order":6},{"statPerLevelRange":[[200.0,0.5]],"caracId":78,"companionId":12,"id":158,"order":7},{"statPerLevelRange":[[200.0,0.4]],"caracId":83,"companionId":12,"id":160,"order":8},{"statPerLevelRange":[[1.0,20.0]],"caracId":33,"companionId":12,"id":161,"order":9},{"statPerLevelRange":[[1.0,10.0]],"caracId":34,"companionId":12,"id":162,"order":10},{"statPerLevelRange":[[1.0,10.0]],"caracId":35,"companionId":12,"id":163,"order":11},{"statPerLevelRange":[[1.0,10.0]],"caracId":36,"companionId":12,"id":164,"order":12},{"statPerLevelRange":[[1.0,10.0]],"caracId":37,"companionId":12,"id":165,"order":13},{"statPerLevelRange":[[1.0,100.0]],"caracId":48,"companionId":12,"id":166,"order":14},{"statPerLevelRange":[[200.0,0.4]],"caracId":82,"companionId":12,"id":167,"order":15},{"statPerLevelRange":[[1.0,55.0],[50.0,5.0],[100.0,10.0],[150.0,20.0],[200.0,40.0]],"caracId":0,"companionId":15,"id":200,"order":0},{"statPerLevelRange":[[1.0,6.0],[200.0,0.029]],"caracId":1,"companionId":15,"id":201,"order":1},{"statPerLevelRange":[[1.0,3.0],[200.0,0.017]],"caracId":23,"companionId":15,"id":202,"order":2},{"statPerLevelRange":[[200.0,0.022]],"caracId":19,"companionId":15,"id":203,"order":3},{"statPerLevelRange":[[1.0,0.2],[50.0,0.2],[100.0,0.4],[150.0,0.6],[200.0,0.8]],"caracId":16,"companionId":15,"id":204,"order":4},{"statPerLevelRange":[[1.0,3.0],[50.0,3.0],[100.0,5.0],[150.0,7.0],[200.0,9.0]],"caracId":25,"companionId":15,"id":205,"order":5},{"statPerLevelRange":[[200.0,0.3]],"caracId":27,"companionId":15,"id":206,"order":6},{"statPerLevelRange":[[200.0,0.3]],"caracId":28,"companionId":15,"id":207,"order":7},{"statPerLevelRange":[[200.0,0.3]],"caracId":78,"companionId":15,"id":208,"order":8},{"statPerLevelRange":[[200.0,0.15]],"caracId":79,"companionId":15,"id":209,"order":9},{"statPerLevelRange":[[200.0,0.5]],"caracId":83,"companionId":15,"id":210,"order":10},{"statPerLevelRange":[[1.0,20.0]],"caracId":33,"companionId":15,"id":211,"order":11},{"statPerLevelRange":[[1.0,10.0]],"caracId":34,"companionId":15,"id":212,"order":12},{"statPerLevelRange":[[1.0,10.0]],"caracId":35,"companionId":15,"id":213,"order":13},{"statPerLevelRange":[[1.0,10.0]],"caracId":36,"companionId":15,"id":214,"order":14},{"statPerLevelRange":[[1.0,10.0]],"caracId":37,"companionId":15,"id":215,"order":15},{"statPerLevelRange":[[1.0,100.0]],"caracId":48,"companionId":15,"id":216,"order":16},{"statPerLevelRange":[[1.0,55.0],[50.0,5.0],[100.0,10.0],[150.0,20.0],[200.0,40.0]],"caracId":0,"companionId":14,"id":217,"order":0},{"statPerLevelRange":[[1.0,6.0],[200.0,0.029]],"caracId":1,"companionId":14,"id":218,"order":1},{"statPerLevelRange":[[1.0,3.0],[200.0,0.017]],"caracId":23,"companionId":14,"id":219,"order":2},{"statPerLevelRange":[[200.0,0.02]],"caracId":19,"companionId":14,"id":220,"order":3},{"statPerLevelRange":[[1.0,0.2],[50.0,0.2],[100.0,0.4],[150.0,0.6],[200.0,0.8]],"caracId":16,"companionId":14,"id":221,"order":4},{"statPerLevelRange":[[1.0,3.0],[50.0,3.0],[100.0,5.0],[150.0,7.0],[200.0,9.0]],"caracId":25,"companionId":14,"id":222,"order":5},{"statPerLevelRange":[[200.0,0.3]],"caracId":27,"companionId":14,"id":223,"order":6},{"statPerLevelRange":[[200.0,0.4]],"caracId":28,"companionId":14,"id":224,"order":7},{"statPerLevelRange":[[200.0,0.375]],"caracId":78,"companionId":14,"id":225,"order":8},{"statPerLevelRange":[[200.0,0.375]],"caracId":79,"companionId":14,"id":226,"order":9},{"statPerLevelRange":[[1.0,10.0]],"caracId":33,"companionId":14,"id":227,"order":10},{"statPerLevelRange":[[1.0,10.0]],"caracId":34,"companionId":14,"id":228,"order":11},{"statPerLevelRange":[[1.0,20.0]],"caracId":35,"companionId":14,"id":229,"order":12},{"statPerLevelRange":[[1.0,10.0]],"caracId":36,"companionId":14,"id":230,"order":13},{"statPerLevelRange":[[1.0,10.0]],"caracId":37,"companionId":14,"id":231,"order":14},{"statPerLevelRange":[[1.0,100.0]],"caracId":48,"companionId":14,"id":232,"order":15},{"statPerLevelRange":[[1.0,55.0],[50.0,5.0],[100.0,10.0],[150.0,20.0],[200.0,40.0]],"caracId":0,"companionId":16,"id":233,"order":0},{"statPerLevelRange":[[1.0,6.0],[200.0,0.029]],"caracId":1,"companionId":16,"id":234,"order":1},{"statPerLevelRange":[[1.0,3.0],[200.0,0.017]],"caracId":23,"companionId":16,"id":235,"order":2},{"statPerLevelRange":[[1.0,3.0],[200.0,0.017]],"caracId":19,"companionId":16,"id":236,"order":3},{"statPerLevelRange":[[1.0,0.2],[50.0,0.2],[100.0,0.4],[150.0,0.6],[200.0,0.8]],"caracId":16,"companionId":16,"id":237,"order":4},{"statPerLevelRange":[[1.0,3.0],[50.0,3.0],[100.0,5.0],[150.0,7.0],[200.0,9.0]],"caracId":25,"companionId":16,"id":238,"order":5},{"statPerLevelRange":[[200.0,0.4]],"caracId":27,"companionId":16,"id":239,"order":6},{"statPerLevelRange":[[200.0,0.3]],"caracId":28,"companionId":16,"id":240,"order":7},{"statPerLevelRange":[[200.0,0.3]],"caracId":78,"companionId":16,"id":241,"order":9},{"statPerLevelRange":[[200.0,0.15]],"caracId":79,"companionId":16,"id":242,"order":10},{"statPerLevelRange":[[1.0,10.0]],"caracId":33,"companionId":16,"id":244,"order":11},{"statPerLevelRange":[[1.0,20.0]],"caracId":34,"companionId":16,"id":245,"order":12},{"statPerLevelRange":[[1.0,10.0]],"caracId":35,"companionId":16,"id":246,"order":13},{"statPerLevelRange":[[1.0,10.0]],"caracId":36,"companionId":16,"id":247,"order":14},{"statPerLevelRange":[[1.0,10.0]],"caracId":37,"companionId":16,"id":248,"order":15},{"statPerLevelRange":[[1.0,100.0]],"caracId":48,"companionId":16,"id":249,"order":16},{"statPerLevelRange":[[1.0,3.0]],"caracId":26,"companionId":16,"id":250,"order":17},{"statPerLevelRange":[[200.0,0.4]],"caracId":83,"companionId":16,"id":251,"order":8},{"statPerLevelRange":[[1.0,55.0],[50.0,5.0],[100.0,10.0],[150.0,20.0],[200.0,40.0]],"caracId":0,"companionId":17,"id":252,"order":0},{"statPerLevelRange":[[1.0,6.0],[200.0,0.029]],"caracId":1,"companionId":17,"id":253,"order":1},{"statPerLevelRange":[[1.0,3.0],[200.0,0.017]],"caracId":23,"companionId":17,"id":254,"order":2},{"statPerLevelRange":[[1.0,3.0],[200.0,0.017]],"caracId":19,"companionId":17,"id":255,"order":3},{"statPerLevelRange":[[1.0,0.2],[50.0,0.2],[100.0,0.4],[150.0,0.6],[200.0,0.8]],"caracId":16,"companionId":17,"id":256,"order":4},{"statPerLevelRange":[[1.0,3.0],[50.0,3.0],[100.0,5.0],[150.0,7.0],[200.0,9.0]],"caracId":25,"companionId":17,"id":257,"order":5},{"statPerLevelRange":[[200.0,0.3]],"caracId":27,"companionId":17,"id":258,"order":6},{"statPerLevelRange":[[200.0,0.3]],"caracId":28,"companionId":17,"id":259,"order":7},{"statPerLevelRange":[[200.0,0.3]],"caracId":78,"companionId":17,"id":260,"order":8},{"statPerLevelRange":[[200.0,0.3]],"caracId":79,"companionId":17,"id":261,"order":9},{"statPerLevelRange":[[1.0,12.0]],"caracId":33,"companionId":17,"id":262,"order":10},{"statPerLevelRange":[[1.0,12.0]],"caracId":34,"companionId":17,"id":263,"order":11},{"statPerLevelRange":[[1.0,12.0]],"caracId":35,"companionId":17,"id":264,"order":12},{"statPerLevelRange":[[1.0,12.0]],"caracId":36,"companionId":17,"id":265,"order":13},{"statPerLevelRange":[[1.0,12.0]],"caracId":37,"companionId":17,"id":266,"order":14},{"statPerLevelRange":[[1.0,100.0]],"caracId":48,"companionId":17,"id":267,"order":15},{"statPerLevelRange":[[200.0,5.0]],"caracId":25,"companionId":13,"id":268,"order":0},{"statPerLevelRange":[[200.0,0.5]],"caracId":78,"companionId":13,"id":269,"order":1},{"statPerLevelRange":[[200.0,0.4]],"caracId":16,"companionId":13,"id":270,"order":2},{"statPerLevelRange":[[200.0,0.4]],"caracId":83,"companionId":13,"id":271,"order":3},{"statPerLevelRange":[[200.0,0.4]],"caracId":82,"companionId":13,"id":272,"order":4},{"statPerLevelRange":[[200.0,0.3]],"caracId":27,"companionId":13,"id":273,"order":5},{"statPerLevelRange":[[200.0,0.3]],"caracId":28,"companionId":13,"id":274,"order":6},{"statPerLevelRange":[[1.0,6.0],[200.0,0.029]],"caracId":1,"companionId":13,"id":275,"order":7},{"statPerLevelRange":[[1.0,50.0],[200.0,13.0]],"caracId":0,"companionId":13,"id":276,"order":8},{"statPerLevelRange":[[1.0,3.0],[200.0,0.017]],"caracId":23,"companionId":13,"id":277,"order":9},{"statPerLevelRange":[[1.0,20.0]],"caracId":33,"companionId":13,"id":278,"order":10},{"statPerLevelRange":[[1.0,100.0]],"caracId":48,"companionId":13,"id":279,"order":11},{"statPerLevelRange":[[1.0,10.0]],"caracId":34,"companionId":13,"id":280,"order":12},{"statPerLevelRange":[[1.0,10.0]],"caracId":35,"companionId":13,"id":281,"order":13},{"statPerLevelRange":[[1.0,10.0]],"caracId":36,"companionId":13,"id":282,"order":14},{"statPerLevelRange":[[1.0,10.0]],"caracId":37,"companionId":13,"id":283,"order":15}]