[{"skins":"2012","gender":0,"assetId":"10_1","id":1,"label":"I","breed":1,"order":0},{"skins":"2013","gender":0,"assetId":"10_2","id":2,"label":"II","breed":1,"order":1},{"skins":"2014","gender":0,"assetId":"10_3","id":3,"label":"III","breed":1,"order":2},{"skins":"2015","gender":0,"assetId":"10_4","id":4,"label":"IV","breed":1,"order":3},{"skins":"2016","gender":0,"assetId":"10_5","id":5,"label":"V","breed":1,"order":4},{"skins":"2017","gender":0,"assetId":"10_6","id":6,"label":"VI","breed":1,"order":5},{"skins":"2018","gender":0,"assetId":"10_7","id":7,"label":"VII","breed":1,"order":6},{"skins":"2019","gender":0,"assetId":"10_8","id":8,"label":"VIII","breed":1,"order":7},{"skins":"2020","gender":1,"assetId":"11_1","id":9,"label":"I","breed":1,"order":0},{"skins":"2021","gender":1,"assetId":"11_2","id":10,"label":"II","breed":1,"order":1},{"skins":"2022","gender":1,"assetId":"11_3","id":11,"label":"III","breed":1,"order":2},{"skins":"2023","gender":1,"assetId":"11_4","id":12,"label":"IV","breed":1,"order":3},{"skins":"2024","gender":1,"assetId":"11_5","id":13,"label":"V","breed":1,"order":4},{"skins":"2025","gender":1,"assetId":"11_6","id":14,"label":"VI","breed":1,"order":5},{"skins":"2026","gender":1,"assetId":"11_7","id":15,"label":"VII","breed":1,"order":6},{"skins":"2027","gender":1,"assetId":"11_8","id":16,"label":"VIII","breed":1,"order":7},{"skins":"2028","gender":0,"assetId":"20_1","id":17,"label":"I","breed":2,"order":0},{"skins":"2029","gender":0,"assetId":"20_2","id":18,"label":"II","breed":2,"order":1},{"skins":"2030","gender":0,"assetId":"20_3","id":19,"label":"III","breed":2,"order":2},{"skins":"2031","gender":0,"assetId":"20_4","id":20,"label":"IV","breed":2,"order":3},{"skins":"2032","gender":0,"assetId":"20_5","id":21,"label":"V","breed":2,"order":4},{"skins":"2033","gender":0,"assetId":"20_6","id":22,"label":"VI","breed":2,"order":5},{"skins":"2034","gender":0,"assetId":"20_7","id":23,"label":"VII","breed":2,"order":6},{"skins":"2035","gender":0,"assetId":"20_8","id":24,"label":"VIII","breed":2,"order":7},{"skins":"2036","gender":1,"assetId":"21_1","id":25,"label":"I","breed":2,"order":0},{"skins":"2037","gender":1,"assetId":"21_2","id":26,"label":"II","breed":2,"order":1},{"skins":"2038","gender":1,"assetId":"21_3","id":27,"label":"III","breed":2,"order":2},{"skins":"2039","gender":1,"assetId":"21_4","id":28,"label":"IV","breed":2,"order":3},{"skins":"2040","gender":1,"assetId":"21_5","id":29,"label":"V","breed":2,"order":4},{"skins":"2041","gender":1,"assetId":"21_6","id":30,"label":"VI","breed":2,"order":5},{"skins":"2042","gender":1,"assetId":"21_7","id":31,"label":"VII","breed":2,"order":6},{"skins":"2043","gender":1,"assetId":"21_8","id":32,"label":"VIII","breed":2,"order":7},{"skins":"2044","gender":0,"assetId":"30_1","id":33,"label":"I","breed":3,"order":0},{"skins":"2045","gender":0,"assetId":"30_2","id":34,"label":"II","breed":3,"order":1},{"skins":"2046","gender":0,"assetId":"30_3","id":35,"label":"III","breed":3,"order":2},{"skins":"2047","gender":0,"assetId":"30_4","id":36,"label":"IV","breed":3,"order":3},{"skins":"2048","gender":0,"assetId":"30_5","id":37,"label":"V","breed":3,"order":4},{"skins":"2049","gender":0,"assetId":"30_6","id":38,"label":"VI","breed":3,"order":5},{"skins":"2050","gender":0,"assetId":"30_7","id":39,"label":"VII","breed":3,"order":6},{"skins":"2051","gender":0,"assetId":"30_8","id":40,"label":"VIII","breed":3,"order":7},{"skins":"2052","gender":1,"assetId":"31_1","id":41,"label":"I","breed":3,"order":0},{"skins":"2053","gender":1,"assetId":"31_2","id":42,"label":"II","breed":3,"order":1},{"skins":"2054","gender":1,"assetId":"31_3","id":43,"label":"III","breed":3,"order":2},{"skins":"2055","gender":1,"assetId":"31_4","id":44,"label":"IV","breed":3,"order":3},{"skins":"2056","gender":1,"assetId":"31_5","id":45,"label":"V","breed":3,"order":4},{"skins":"2057","gender":1,"assetId":"31_6","id":46,"label":"VI","breed":3,"order":5},{"skins":"2058","gender":1,"assetId":"31_7","id":47,"label":"VII","breed":3,"order":6},{"skins":"2059","gender":1,"assetId":"31_8","id":48,"label":"VIII","breed":3,"order":7},{"skins":"2060","gender":0,"assetId":"40_1","id":49,"label":"I","breed":4,"order":0},{"skins":"2061","gender":0,"assetId":"40_2","id":50,"label":"II","breed":4,"order":1},{"skins":"2062","gender":0,"assetId":"40_3","id":51,"label":"III","breed":4,"order":2},{"skins":"2063","gender":0,"assetId":"40_4","id":52,"label":"IV","breed":4,"order":3},{"skins":"2064","gender":0,"assetId":"40_5","id":53,"label":"V","breed":4,"order":4},{"skins":"2065","gender":0,"assetId":"40_6","id":54,"label":"VI","breed":4,"order":5},{"skins":"2066","gender":0,"assetId":"40_7","id":55,"label":"VII","breed":4,"order":6},{"skins":"2067","gender":0,"assetId":"40_8","id":56,"label":"VIII","breed":4,"order":7},{"skins":"2068","gender":1,"assetId":"41_1","id":57,"label":"I","breed":4,"order":0},{"skins":"2069","gender":1,"assetId":"41_2","id":58,"label":"II","breed":4,"order":1},{"skins":"2070","gender":1,"assetId":"41_3","id":59,"label":"III","breed":4,"order":2},{"skins":"2071","gender":1,"assetId":"41_4","id":60,"label":"IV","breed":4,"order":3},{"skins":"2072","gender":1,"assetId":"41_5","id":61,"label":"V","breed":4,"order":4},{"skins":"2073","gender":1,"assetId":"41_6","id":62,"label":"VI","breed":4,"order":5},{"skins":"2074","gender":1,"assetId":"41_7","id":63,"label":"VII","breed":4,"order":6},{"skins":"2075","gender":1,"assetId":"41_8","id":64,"label":"VIII","breed":4,"order":7},{"skins":"2076","gender":0,"assetId":"50_1","id":65,"label":"I","breed":5,"order":0},{"skins":"2077","gender":0,"assetId":"50_2","id":66,"label":"II","breed":5,"order":1},{"skins":"2078","gender":0,"assetId":"50_3","id":67,"label":"III","breed":5,"order":2},{"skins":"2079","gender":0,"assetId":"50_4","id":68,"label":"IV","breed":5,"order":3},{"skins":"2080","gender":0,"assetId":"50_5","id":69,"label":"V","breed":5,"order":4},{"skins":"2081","gender":0,"assetId":"50_6","id":70,"label":"VI","breed":5,"order":5},{"skins":"2082","gender":0,"assetId":"50_7","id":71,"label":"VII","breed":5,"order":6},{"skins":"2083","gender":0,"assetId":"50_8","id":72,"label":"VIII","breed":5,"order":7},{"skins":"2084","gender":1,"assetId":"51_1","id":73,"label":"I","breed":5,"order":0},{"skins":"2085","gender":1,"assetId":"51_2","id":74,"label":"II","breed":5,"order":1},{"skins":"2086","gender":1,"assetId":"51_3","id":75,"label":"III","breed":5,"order":2},{"skins":"2087","gender":1,"assetId":"51_4","id":76,"label":"IV","breed":5,"order":3},{"skins":"2088","gender":1,"assetId":"51_5","id":77,"label":"V","breed":5,"order":4},{"skins":"2089","gender":1,"assetId":"51_6","id":78,"label":"VI","breed":5,"order":5},{"skins":"2090","gender":1,"assetId":"51_7","id":79,"label":"VII","breed":5,"order":6},{"skins":"2091","gender":1,"assetId":"51_8","id":80,"label":"VIII","breed":5,"order":7},{"skins":"2092","gender":0,"assetId":"60_1","id":81,"label":"I","breed":6,"order":0},{"skins":"2093","gender":0,"assetId":"60_2","id":82,"label":"II","breed":6,"order":1},{"skins":"2094","gender":0,"assetId":"60_3","id":83,"label":"III","breed":6,"order":2},{"skins":"2095","gender":0,"assetId":"60_4","id":84,"label":"IV","breed":6,"order":3},{"skins":"2096","gender":0,"assetId":"60_5","id":85,"label":"V","breed":6,"order":4},{"skins":"2097","gender":0,"assetId":"60_6","id":86,"label":"VI","breed":6,"order":5},{"skins":"2098","gender":0,"assetId":"60_7","id":87,"label":"VII","breed":6,"order":6},{"skins":"2099","gender":0,"assetId":"60_8","id":88,"label":"VIII","breed":6,"order":7},{"skins":"2100","gender":1,"assetId":"61_1","id":89,"label":"I","breed":6,"order":0},{"skins":"2101","gender":1,"assetId":"61_2","id":90,"label":"II","breed":6,"order":1},{"skins":"2102","gender":1,"assetId":"61_3","id":91,"label":"III","breed":6,"order":2},{"skins":"2103","gender":1,"assetId":"61_4","id":92,"label":"IV","breed":6,"order":3},{"skins":"2104","gender":1,"assetId":"61_5","id":93,"label":"V","breed":6,"order":4},{"skins":"2105","gender":1,"assetId":"61_6","id":94,"label":"VI","breed":6,"order":5},{"skins":"2106","gender":1,"assetId":"61_7","id":95,"label":"VII","breed":6,"order":6},{"skins":"2107","gender":1,"assetId":"61_8","id":96,"label":"VIII","breed":6,"order":7},{"skins":"2108","gender":0,"assetId":"70_1","id":97,"label":"I","breed":7,"order":0},{"skins":"2109","gender":0,"assetId":"70_2","id":98,"label":"II","breed":7,"order":1},{"skins":"2110","gender":0,"assetId":"70_3","id":99,"label":"III","breed":7,"order":2},{"skins":"2111","gender":0,"assetId":"70_4","id":100,"label":"IV","breed":7,"order":3},{"skins":"2112","gender":0,"assetId":"70_5","id":101,"label":"V","breed":7,"order":4},{"skins":"2113","gender":0,"assetId":"70_6","id":102,"label":"VI","breed":7,"order":5},{"skins":"2114","gender":0,"assetId":"70_7","id":103,"label":"VII","breed":7,"order":6},{"skins":"2115","gender":0,"assetId":"70_8","id":104,"label":"VIII","breed":7,"order":7},{"skins":"2116","gender":1,"assetId":"71_1","id":105,"label":"I","breed":7,"order":0},{"skins":"2117","gender":1,"assetId":"71_2","id":106,"label":"II","breed":7,"order":1},{"skins":"2118","gender":1,"assetId":"71_3","id":107,"label":"III","breed":7,"order":2},{"skins":"2119","gender":1,"assetId":"71_4","id":108,"label":"IV","breed":7,"order":3},{"skins":"2120","gender":1,"assetId":"71_5","id":109,"label":"V","breed":7,"order":4},{"skins":"2121","gender":1,"assetId":"71_6","id":110,"label":"VI","breed":7,"order":5},{"skins":"2122","gender":1,"assetId":"71_7","id":111,"label":"VII","breed":7,"order":6},{"skins":"2123","gender":1,"assetId":"71_8","id":112,"label":"VIII","breed":7,"order":7},{"skins":"2124","gender":0,"assetId":"80_1","id":113,"label":"I","breed":8,"order":0},{"skins":"2125","gender":0,"assetId":"80_2","id":114,"label":"II","breed":8,"order":1},{"skins":"2126","gender":0,"assetId":"80_3","id":115,"label":"III","breed":8,"order":2},{"skins":"2127","gender":0,"assetId":"80_4","id":116,"label":"IV","breed":8,"order":3},{"skins":"2128","gender":0,"assetId":"80_5","id":117,"label":"V","breed":8,"order":4},{"skins":"2129","gender":0,"assetId":"80_6","id":118,"label":"VI","breed":8,"order":5},{"skins":"2130","gender":0,"assetId":"80_7","id":119,"label":"VII","breed":8,"order":6},{"skins":"2131","gender":0,"assetId":"80_8","id":120,"label":"VIII","breed":8,"order":7},{"skins":"2132","gender":1,"assetId":"81_1","id":121,"label":"I","breed":8,"order":0},{"skins":"2133","gender":1,"assetId":"81_2","id":122,"label":"II","breed":8,"order":1},{"skins":"2134","gender":1,"assetId":"81_3","id":123,"label":"III","breed":8,"order":2},{"skins":"2135","gender":1,"assetId":"81_4","id":124,"label":"IV","breed":8,"order":3},{"skins":"2136","gender":1,"assetId":"81_5","id":125,"label":"V","breed":8,"order":4},{"skins":"2137","gender":1,"assetId":"81_6","id":126,"label":"VI","breed":8,"order":5},{"skins":"2138","gender":1,"assetId":"81_7","id":127,"label":"VII","breed":8,"order":6},{"skins":"2139","gender":1,"assetId":"81_8","id":128,"label":"VIII","breed":8,"order":7},{"skins":"2140","gender":0,"assetId":"90_1","id":129,"label":"I","breed":9,"order":0},{"skins":"2141","gender":0,"assetId":"90_2","id":130,"label":"II","breed":9,"order":1},{"skins":"2142","gender":0,"assetId":"90_3","id":131,"label":"III","breed":9,"order":2},{"skins":"2143","gender":0,"assetId":"90_4","id":132,"label":"IV","breed":9,"order":3},{"skins":"2144","gender":0,"assetId":"90_5","id":133,"label":"V","breed":9,"order":4},{"skins":"2145","gender":0,"assetId":"90_6","id":134,"label":"VI","breed":9,"order":5},{"skins":"2146","gender":0,"assetId":"90_7","id":135,"label":"VII","breed":9,"order":6},{"skins":"2147","gender":0,"assetId":"90_8","id":136,"label":"VIII","breed":9,"order":7},{"skins":"2148","gender":1,"assetId":"91_1","id":137,"label":"I","breed":9,"order":0},{"skins":"2149","gender":1,"assetId":"91_2","id":138,"label":"II","breed":9,"order":1},{"skins":"2150","gender":1,"assetId":"91_3","id":139,"label":"III","breed":9,"order":2},{"skins":"2151","gender":1,"assetId":"91_4","id":140,"label":"IV","breed":9,"order":3},{"skins":"2152","gender":1,"assetId":"91_5","id":141,"label":"V","breed":9,"order":4},{"skins":"2153","gender":1,"assetId":"91_6","id":142,"label":"VI","breed":9,"order":5},{"skins":"2154","gender":1,"assetId":"91_7","id":143,"label":"VII","breed":9,"order":6},{"skins":"2155","gender":1,"assetId":"91_8","id":144,"label":"VIII","breed":9,"order":7},{"skins":"2156","gender":0,"assetId":"100_1","id":145,"label":"I","breed":10,"order":0},{"skins":"2157","gender":0,"assetId":"100_2","id":146,"label":"II","breed":10,"order":1},{"skins":"2158","gender":0,"assetId":"100_3","id":147,"label":"III","breed":10,"order":2},{"skins":"2159","gender":0,"assetId":"100_4","id":148,"label":"IV","breed":10,"order":3},{"skins":"2160","gender":0,"assetId":"100_5","id":149,"label":"V","breed":10,"order":4},{"skins":"2161","gender":0,"assetId":"100_6","id":150,"label":"VI","breed":10,"order":5},{"skins":"2162","gender":0,"assetId":"100_7","id":151,"label":"VII","breed":10,"order":6},{"skins":"2163","gender":0,"assetId":"100_8","id":152,"label":"VIII","breed":10,"order":7},{"skins":"2164","gender":1,"assetId":"101_1","id":153,"label":"I","breed":10,"order":0},{"skins":"2165","gender":1,"assetId":"101_2","id":154,"label":"II","breed":10,"order":1},{"skins":"2166","gender":1,"assetId":"101_3","id":155,"label":"III","breed":10,"order":2},{"skins":"2167","gender":1,"assetId":"101_4","id":156,"label":"IV","breed":10,"order":3},{"skins":"2168","gender":1,"assetId":"101_5","id":157,"label":"V","breed":10,"order":4},{"skins":"2169","gender":1,"assetId":"101_6","id":158,"label":"VI","breed":10,"order":5},{"skins":"2170","gender":1,"assetId":"101_7","id":159,"label":"VII","breed":10,"order":6},{"skins":"2171","gender":1,"assetId":"101_8","id":160,"label":"VIII","breed":10,"order":7},{"skins":"2172","gender":0,"assetId":"110_1","id":161,"label":"I","breed":11,"order":0},{"skins":"2173","gender":0,"assetId":"110_2","id":162,"label":"II","breed":11,"order":1},{"skins":"2174","gender":0,"assetId":"110_3","id":163,"label":"III","breed":11,"order":2},{"skins":"2175","gender":0,"assetId":"110_4","id":164,"label":"IV","breed":11,"order":3},{"skins":"2176","gender":0,"assetId":"110_5","id":165,"label":"V","breed":11,"order":4},{"skins":"2177","gender":0,"assetId":"110_6","id":166,"label":"VI","breed":11,"order":5},{"skins":"2178","gender":0,"assetId":"110_7","id":167,"label":"VII","breed":11,"order":6},{"skins":"2179","gender":0,"assetId":"110_8","id":168,"label":"VIII","breed":11,"order":7},{"skins":"2180","gender":1,"assetId":"111_1","id":169,"label":"I","breed":11,"order":0},{"skins":"2181","gender":1,"assetId":"111_2","id":170,"label":"II","breed":11,"order":1},{"skins":"2182","gender":1,"assetId":"111_3","id":171,"label":"III","breed":11,"order":2},{"skins":"2183","gender":1,"assetId":"111_4","id":172,"label":"IV","breed":11,"order":3},{"skins":"2184","gender":1,"assetId":"111_5","id":173,"label":"V","breed":11,"order":4},{"skins":"2185","gender":1,"assetId":"111_6","id":174,"label":"VI","breed":11,"order":5},{"skins":"2186","gender":1,"assetId":"111_7","id":175,"label":"VII","breed":11,"order":6},{"skins":"2187","gender":1,"assetId":"111_8","id":176,"label":"VIII","breed":11,"order":7},{"skins":"2188","gender":0,"assetId":"120_1","id":177,"label":"I","breed":12,"order":0},{"skins":"2189","gender":0,"assetId":"120_2","id":178,"label":"II","breed":12,"order":1},{"skins":"2190","gender":0,"assetId":"120_3","id":179,"label":"III","breed":12,"order":2},{"skins":"2191","gender":0,"assetId":"120_4","id":180,"label":"IV","breed":12,"order":3},{"skins":"2192","gender":0,"assetId":"120_5","id":181,"label":"V","breed":12,"order":4},{"skins":"2193","gender":0,"assetId":"120_6","id":182,"label":"VI","breed":12,"order":5},{"skins":"2194","gender":0,"assetId":"120_7","id":183,"label":"VII","breed":12,"order":6},{"skins":"2195","gender":0,"assetId":"120_8","id":184,"label":"VIII","breed":12,"order":7},{"skins":"2196","gender":1,"assetId":"121_1","id":185,"label":"I","breed":12,"order":0},{"skins":"2197","gender":1,"assetId":"121_2","id":186,"label":"II","breed":12,"order":1},{"skins":"2198","gender":1,"assetId":"121_3","id":187,"label":"III","breed":12,"order":2},{"skins":"2199","gender":1,"assetId":"121_4","id":188,"label":"IV","breed":12,"order":3},{"skins":"2200","gender":1,"assetId":"121_5","id":189,"label":"V","breed":12,"order":4},{"skins":"2201","gender":1,"assetId":"121_6","id":190,"label":"VI","breed":12,"order":5},{"skins":"2202","gender":1,"assetId":"121_7","id":191,"label":"VII","breed":12,"order":6},{"skins":"2203","gender":1,"assetId":"121_8","id":192,"label":"VIII","breed":12,"order":7},{"skins":"2204","gender":0,"assetId":"130_1","id":193,"label":"I","breed":13,"order":0},{"skins":"2205","gender":0,"assetId":"130_2","id":194,"label":"II","breed":13,"order":1},{"skins":"2206","gender":0,"assetId":"130_3","id":195,"label":"III","breed":13,"order":2},{"skins":"2207","gender":0,"assetId":"130_4","id":196,"label":"IV","breed":13,"order":3},{"skins":"2208","gender":0,"assetId":"130_5","id":197,"label":"V","breed":13,"order":4},{"skins":"2209","gender":0,"assetId":"130_6","id":198,"label":"VI","breed":13,"order":5},{"skins":"2210","gender":0,"assetId":"130_7","id":199,"label":"VII","breed":13,"order":6},{"skins":"2211","gender":0,"assetId":"130_8","id":200,"label":"VIII","breed":13,"order":7},{"skins":"2212","gender":1,"assetId":"131_1","id":201,"label":"I","breed":13,"order":0},{"skins":"2213","gender":1,"assetId":"131_2","id":202,"label":"II","breed":13,"order":1},{"skins":"2214","gender":1,"assetId":"131_3","id":203,"label":"III","breed":13,"order":2},{"skins":"2215","gender":1,"assetId":"131_4","id":204,"label":"IV","breed":13,"order":3},{"skins":"2216","gender":1,"assetId":"131_5","id":205,"label":"V","breed":13,"order":4},{"skins":"2217","gender":1,"assetId":"131_6","id":206,"label":"VI","breed":13,"order":5},{"skins":"2218","gender":1,"assetId":"131_7","id":207,"label":"VII","breed":13,"order":6},{"skins":"2219","gender":1,"assetId":"131_8","id":208,"label":"VIII","breed":13,"order":7},{"skins":"2220","gender":0,"assetId":"140_1","id":209,"label":"I","breed":14,"order":0},{"skins":"2221","gender":0,"assetId":"140_2","id":210,"label":"II","breed":14,"order":1},{"skins":"2222","gender":0,"assetId":"140_3","id":211,"label":"III","breed":14,"order":2},{"skins":"2223","gender":0,"assetId":"140_4","id":212,"label":"IV","breed":14,"order":3},{"skins":"2224","gender":0,"assetId":"140_5","id":213,"label":"V","breed":14,"order":4},{"skins":"2225","gender":0,"assetId":"140_6","id":214,"label":"VI","breed":14,"order":5},{"skins":"2226","gender":0,"assetId":"140_7","id":215,"label":"VII","breed":14,"order":6},{"skins":"2227","gender":0,"assetId":"140_8","id":216,"label":"VIII","breed":14,"order":7},{"skins":"2228","gender":1,"assetId":"141_1","id":217,"label":"I","breed":14,"order":0},{"skins":"2229","gender":1,"assetId":"141_2","id":218,"label":"II","breed":14,"order":1},{"skins":"2230","gender":1,"assetId":"141_3","id":219,"label":"III","breed":14,"order":2},{"skins":"2231","gender":1,"assetId":"141_4","id":220,"label":"IV","breed":14,"order":3},{"skins":"2232","gender":1,"assetId":"141_5","id":221,"label":"V","breed":14,"order":4},{"skins":"2233","gender":1,"assetId":"141_6","id":222,"label":"VI","breed":14,"order":5},{"skins":"2234","gender":1,"assetId":"141_7","id":223,"label":"VII","breed":14,"order":6},{"skins":"2235","gender":1,"assetId":"141_8","id":224,"label":"VIII","breed":14,"order":7},{"skins":"2236","gender":0,"assetId":"150_1","id":225,"label":"I","breed":15,"order":0},{"skins":"2237","gender":0,"assetId":"150_2","id":226,"label":"II","breed":15,"order":1},{"skins":"2238","gender":0,"assetId":"150_3","id":227,"label":"III","breed":15,"order":2},{"skins":"2239","gender":0,"assetId":"150_4","id":228,"label":"IV","breed":15,"order":3},{"skins":"2240","gender":0,"assetId":"150_5","id":229,"label":"V","breed":15,"order":4},{"skins":"2241","gender":0,"assetId":"150_6","id":230,"label":"VI","breed":15,"order":5},{"skins":"2242","gender":0,"assetId":"150_7","id":231,"label":"VII","breed":15,"order":6},{"skins":"2243","gender":0,"assetId":"150_8","id":232,"label":"VIII","breed":15,"order":7},{"skins":"2244","gender":1,"assetId":"151_1","id":233,"label":"I","breed":15,"order":0},{"skins":"2245","gender":1,"assetId":"151_2","id":234,"label":"II","breed":15,"order":1},{"skins":"2246","gender":1,"assetId":"151_3","id":235,"label":"III","breed":15,"order":2},{"skins":"2247","gender":1,"assetId":"151_4","id":236,"label":"IV","breed":15,"order":3},{"skins":"2248","gender":1,"assetId":"151_5","id":237,"label":"V","breed":15,"order":4},{"skins":"2249","gender":1,"assetId":"151_6","id":238,"label":"VI","breed":15,"order":5},{"skins":"2250","gender":1,"assetId":"151_7","id":239,"label":"VII","breed":15,"order":6},{"skins":"2251","gender":1,"assetId":"151_8","id":240,"label":"VIII","breed":15,"order":7},{"skins":"3183","gender":0,"assetId":"160_1","id":241,"label":"I","breed":16,"order":0},{"skins":"3184","gender":0,"assetId":"160_2","id":242,"label":"II","breed":16,"order":1},{"skins":"3185","gender":0,"assetId":"160_3","id":243,"label":"III","breed":16,"order":2},{"skins":"3186","gender":0,"assetId":"160_4","id":244,"label":"IV","breed":16,"order":3},{"skins":"3187","gender":0,"assetId":"160_5","id":245,"label":"V","breed":16,"order":4},{"skins":"3188","gender":0,"assetId":"160_6","id":246,"label":"VI","breed":16,"order":5},{"skins":"3189","gender":0,"assetId":"160_7","id":247,"label":"VII","breed":16,"order":6},{"skins":"3190","gender":0,"assetId":"160_8","id":248,"label":"VIII","breed":16,"order":7},{"skins":"3191","gender":1,"assetId":"161_1","id":249,"label":"I","breed":16,"order":0},{"skins":"3192","gender":1,"assetId":"161_2","id":250,"label":"II","breed":16,"order":1},{"skins":"3193","gender":1,"assetId":"161_3","id":251,"label":"III","breed":16,"order":2},{"skins":"3194","gender":1,"assetId":"161_4","id":252,"label":"IV","breed":16,"order":3},{"skins":"3195","gender":1,"assetId":"161_5","id":253,"label":"V","breed":16,"order":4},{"skins":"3196","gender":1,"assetId":"161_6","id":254,"label":"VI","breed":16,"order":5},{"skins":"3197","gender":1,"assetId":"161_7","id":255,"label":"VII","breed":16,"order":6},{"skins":"3198","gender":1,"assetId":"161_8","id":256,"label":"VIII","breed":16,"order":7},{"skins":"3289","gender":0,"assetId":"170_1","id":257,"label":"I","breed":17,"order":0},{"skins":"3290","gender":0,"assetId":"170_2","id":258,"label":"II","breed":17,"order":1},{"skins":"3291","gender":0,"assetId":"170_3","id":259,"label":"III","breed":17,"order":2},{"skins":"3292","gender":0,"assetId":"170_4","id":260,"label":"IV","breed":17,"order":3},{"skins":"3293","gender":0,"assetId":"170_5","id":261,"label":"V","breed":17,"order":4},{"skins":"3294","gender":0,"assetId":"170_6","id":262,"label":"VI","breed":17,"order":5},{"skins":"3295","gender":0,"assetId":"170_7","id":263,"label":"VII","breed":17,"order":6},{"skins":"3296","gender":0,"assetId":"170_8","id":264,"label":"VIII","breed":17,"order":7},{"skins":"3297","gender":1,"assetId":"171_1","id":265,"label":"I","breed":17,"order":0},{"skins":"3298","gender":1,"assetId":"171_2","id":266,"label":"II","breed":17,"order":1},{"skins":"3299","gender":1,"assetId":"171_3","id":267,"label":"III","breed":17,"order":2},{"skins":"3300","gender":1,"assetId":"171_4","id":268,"label":"IV","breed":17,"order":3},{"skins":"3301","gender":1,"assetId":"171_5","id":269,"label":"V","breed":17,"order":4},{"skins":"3302","gender":1,"assetId":"171_6","id":270,"label":"VI","breed":17,"order":5},{"skins":"3303","gender":1,"assetId":"171_7","id":271,"label":"VII","breed":17,"order":6},{"skins":"3304","gender":1,"assetId":"171_8","id":272,"label":"VIII","breed":17,"order":7},{"skins":"3502","gender":0,"assetId":"180_1","id":273,"label":"I","breed":18,"order":0},{"skins":"3510","gender":1,"assetId":"181_1","id":275,"label":"I","breed":18,"order":0},{"skins":"3511","gender":1,"assetId":"181_2","id":276,"label":"II","breed":18,"order":1},{"skins":"3512","gender":1,"assetId":"181_3","id":277,"label":"III","breed":18,"order":2},{"skins":"3513","gender":1,"assetId":"181_4","id":280,"label":"IV","breed":18,"order":3},{"skins":"3514","gender":1,"assetId":"181_5","id":281,"label":"V","breed":18,"order":4},{"skins":"3515","gender":1,"assetId":"181_6","id":282,"label":"VI","breed":18,"order":5},{"skins":"3516","gender":1,"assetId":"181_7","id":283,"label":"VII","breed":18,"order":6},{"skins":"3517","gender":1,"assetId":"181_8","id":284,"label":"VIII","breed":18,"order":7},{"skins":"3503","gender":0,"assetId":"180_2","id":285,"label":"II","breed":18,"order":1},{"skins":"3504","gender":0,"assetId":"180_3","id":286,"label":"III","breed":18,"order":2},{"skins":"3505","gender":0,"assetId":"180_4","id":287,"label":"IV","breed":18,"order":3},{"skins":"3506","gender":0,"assetId":"180_5","id":288,"label":"V","breed":18,"order":4},{"skins":"3507","gender":0,"assetId":"180_6","id":289,"label":"VI","breed":18,"order":5},{"skins":"3508","gender":0,"assetId":"180_7","id":290,"label":"VII","breed":18,"order":6},{"skins":"3509","gender":0,"assetId":"180_8","id":291,"label":"VIII","breed":18,"order":7}]